cli/__init__.py
cli/accounts.py
cli/cli.py
cli/config.py
cli/datasets.py
cli/jobs.py
cli/loader.py
cli/logs.py
cli/projects.py
cli/sims.py
cli/transforms.py
cli/utils.py
test/__init__.py
test/client.py
zpy/__init__.py
zpy/_version.py
zpy/assets.py
zpy/blender.py
zpy/camera.py
zpy/client.py
zpy/client_util.py
zpy/color.py
zpy/colors.json
zpy/files.py
zpy/gin.py
zpy/hdris.py
zpy/image.py
zpy/kdtree.py
zpy/keypoints.py
zpy/logging.py
zpy/material.py
zpy/ml.py
zpy/nodes.py
zpy/objects.py
zpy/output.py
zpy/output_coco.py
zpy/output_csv.py
zpy/output_mot.py
zpy/output_zumo.py
zpy/render.py
zpy/requests.py
zpy/saver.py
zpy/saver_image.py
zpy/saver_video.py
zpy/viz.py
zpy_addon/__init__.py
zpy_addon/execute_panel.py
zpy_addon/export_panel.py
zpy_addon/output_panel.py
zpy_addon/script_panel.py
zpy_addon/segment_panel.py
zpy_zumo-1.4.0.dist-info/LICENSE
zpy_zumo-1.4.0.dist-info/METADATA
zpy_zumo-1.4.0.dist-info/WHEEL
zpy_zumo-1.4.0.dist-info/entry_points.txt
zpy_zumo-1.4.0.dist-info/top_level.txt
zpy_zumo-1.4.0.dist-info/RECORD
