Metadata-Version: 2.1
Name: zpy-zumo
Version: 1.4.0
Summary: Create synthetic data with Blender.
Home-page: https://github.com/ZumoLabs/zpy
Author: Zumo Labs
Author-email: infra@zumolabs.ai
License: UNKNOWN
Platform: UNKNOWN
License-File: LICENSE
Requires-Dist: numpy (==1.19.4)
Requires-Dist: gin-config (==0.3.0)
Requires-Dist: versioneer
Requires-Dist: scikit-image (==0.18.1)
Requires-Dist: shapely (==1.7.1)
Requires-Dist: ptvsd (==4.3.2)
Requires-Dist: seaborn (==0.11.0)
Requires-Dist: zmq
Requires-Dist: pyyaml
Requires-Dist: requests
Requires-Dist: click
Requires-Dist: table-logger (==0.3.6)
Requires-Dist: tqdm
Requires-Dist: pydash
